SparkleLogging/Interfaces.py
SparkleLogging/__init__.py
SparkleLogging/dependencies.py
SparkleLogging/core/__init__.py
SparkleLogging/core/_excformat.py
SparkleLogging/core/_formatter.py
SparkleLogging/core/_handler.py
SparkleLogging/core/_level.py
SparkleLogging/core/_logger.py
SparkleLogging/core/_manager.py
SparkleLogging/plugins/DecoratorsTools.py
SparkleLogging/plugins/__init__.py
SparkleLogging/utils/__init__.py
SparkleLogging/utils/_color.py
SparkleLogging/utils/_types.py
SparkleLogging_new-1.0.1.dist-info/METADATA
SparkleLogging_new-1.0.1.dist-info/WHEEL
SparkleLogging_new-1.0.1.dist-info/top_level.txt
SparkleLogging_new-1.0.1.dist-info/RECORD
