Metadata-Version: 2.1
Name: SparkleLogging-new
Version: 1.0.1
Summary: A logging library for Python
Home-page: https://github.com/KOKOMI12345/NewSparkleLogging
Author: 花火official
Author-email: 3072252442@qq.com
Classifier: Programming Language :: Python :: 3
Classifier: License :: OSI Approved :: MIT License
Classifier: Operating System :: OS Independent
